convert2snn.py
models_rate.py
population.py
rate.py
temporal.py
utils.py
convert2snn-0.0.3.dist-info/LICENSE
convert2snn-0.0.3.dist-info/METADATA
convert2snn-0.0.3.dist-info/WHEEL
convert2snn-0.0.3.dist-info/top_level.txt
convert2snn-0.0.3.dist-info/RECORD
