Metadata-Version: 2.1
Name: convert2snn
Version: 0.0.3
Summary: Convert conventional to spiking neural networks.
Home-page: https://github.com/EtienneMueller/Convert2SNN
Author: Etienne Mueller
Author-email: etienne.mueller@tum.de
License: UNKNOWN
Project-URL: Bug Tracker, https://github.com/EtienneMueller/Convert2SNN/issues
Platform: UNKNOWN
Classifier: Programming Language :: Python :: 3.7
Classifier: License :: OSI Approved :: MIT License
Classifier: Operating System :: OS Independent
Requires-Python: >=3.7
License-File: LICENSE
Requires-Dist: tensorflow (>=2.7.0)
Provides-Extra: dev
Requires-Dist: pytest (>=3.7) ; extra == 'dev'
Requires-Dist: check-manifest (>=0.47twine>=4.0) ; extra == 'dev'
